litelistener/__init__.py
litelistener/listener.py
litelistener-0.1.4.dist-info/METADATA
litelistener-0.1.4.dist-info/WHEEL
litelistener-0.1.4.dist-info/RECORD
