Metadata-Version: 2.4
Name: litelistener
Version: 0.1.4
Summary: Uses liteclient to listen for keys in a redis-like queue
Author-email: Joe Pasquantonio <joe.pasquantonio@gmail.com>
Requires-Python: >=3.11
Requires-Dist: liteclient
